sio/__init__.py
sio/__version__.py
sio-0.0.2.dist-info/LICENSE
sio-0.0.2.dist-info/METADATA
sio-0.0.2.dist-info/WHEEL
sio-0.0.2.dist-info/top_level.txt
sio-0.0.2.dist-info/RECORD
