Metadata-Version: 2.1
Name: sio
Version: 0.0.2
Summary: SIO is short IO that even shorter that ShortIO
Home-page: https://github.com/byshyk/sio
Author: Yaraslau Byshyk
Author-email: dev@shyk.by
License: WTFPL
Platform: UNKNOWN
Requires-Dist: shortio (>=0.1.0)
